base_api_utils/__init__.py
base_api_utils/urls.py
base_api_utils/domain/__init__.py
base_api_utils/domain/event_message.py
base_api_utils/domain/event_message_factory.py
base_api_utils/domain/events.py
base_api_utils/dtos/__init__.py
base_api_utils/dtos/authz_user.py
base_api_utils/fields/__init__.py
base_api_utils/fields/email_list_field.py
base_api_utils/filters/__init__.py
base_api_utils/filters/base_filter.py
base_api_utils/filters/custom_ordering_filter.py
base_api_utils/filters/filter_utils_mixin.py
base_api_utils/handlers/__init__.py
base_api_utils/handlers/base_event_handler.py
base_api_utils/handlers/sponsor_event_handler.py
base_api_utils/handlers/sponsorship_addon_event_handler.py
base_api_utils/handlers/sponsorship_event_handler.py
base_api_utils/handlers/summit_event_handler.py
base_api_utils/ioc/__init__.py
base_api_utils/ioc/container.py
base_api_utils/models/__init__.py
base_api_utils/models/item_image.py
base_api_utils/security/__init__.py
base_api_utils/security/abstract_access_token_service.py
base_api_utils/security/abstract_oauth2_api_client.py
base_api_utils/security/access_token_service.py
base_api_utils/security/check_sponsor_user_permissions.py
base_api_utils/security/group_required.py
base_api_utils/security/oauth2_authentication.py
base_api_utils/security/oauth2_client_factory.py
base_api_utils/security/oauth2_scope_required.py
base_api_utils/security/permission_event_handler.py
base_api_utils/security/shared.py
base_api_utils/security/user_permissions_service.py
base_api_utils/serializers/__init__.py
base_api_utils/serializers/base_model_serializer.py
base_api_utils/serializers/email_list_char_field.py
base_api_utils/serializers/nullable_slug_related_field.py
base_api_utils/serializers/serializers_registry.py
base_api_utils/serializers/task_result_serializer.py
base_api_utils/serializers/timestamp_field.py
base_api_utils/services/__init__.py
base_api_utils/services/abstract_domain_events_service.py
base_api_utils-1.1.75.dist-info/licenses/LICENSE
base_api_utils-1.1.75.dist-info/METADATA
base_api_utils-1.1.75.dist-info/WHEEL
base_api_utils-1.1.75.dist-info/top_level.txt
base_api_utils-1.1.75.dist-info/RECORD
