Metadata-Version: 2.4
Name: base-api-utils
Version: 1.1.75
Summary: Django Rest Framework micro services common utilities
Author-email: Román Gutierrez <roman@tipit.net>, Sebastian Marcet <sebastian@tipit.net>
Project-URL: Homepage, https://github.com/fntechgit/base-api-utils
Classifier: Programming Language :: Python :: 3
Classifier: Operating System :: OS Independent
Requires-Python: >=3.10
License-File: LICENSE
Requires-Dist: boto3
Requires-Dist: celery
Requires-Dist: Django
Requires-Dist: django-celery-results
Requires-Dist: django_filter
Requires-Dist: djangorestframework>=3.15.2
Requires-Dist: drf-spectacular
Requires-Dist: injector
Requires-Dist: oauthlib
Requires-Dist: pika
Requires-Dist: pybreaker
Requires-Dist: requests
Requires-Dist: requests-oauthlib
Dynamic: license-file
